{
  "ut": 1712631812,
  "date_str": "2024-04-09",
  "newspaper_id": "daily-mirror",
  "url": "https://www.dailymirror.lk/obituaries/GAMAGE-RANJITH-VIDURA-GAMAGE/378-280540",
  "raw_title": "GAMAGE \u2013 RANJITH VIDURA GAMAGE",
  "raw_body": "Son of the late William Kokmaduwa Gamage and the late Daisy Gamage (nee Jayasinghe), husband of Girty (nee Abeywickrama), father of Rajiv and Yasantha, father-in-law of Thuseimi (nee Walpita), grandfather of Kiyara and Liana, brother of Manel, Thilak and Suranganee (all deceased), brother-in-law of Carl Hapuarachchi, Priyalal Wickramasuriya (both deceased), Nimalka (nee Wijayatilake), Chandra Abeywickrama, Thamadara Munideva and TharangaAbeysingh "
}