{
  "ut": 1699660800.0,
  "date_str": "2023-11-11",
  "newspaper_id": "daily-news",
  "i": 1,
  "url": "https://www.dailynews.lk/2023/11/11/obituaries/224721/obituaries-102/",
  "raw_text": "BANDARA \u2013 THILAK (G.P.K.) former Manager of Grindlays Bank,\u200b Country Manager of Qantas Airways & Cox and Kings. Dearly beloved husband of Shani,\u200b loving father of Yohan,\u200b Tanya and Rajith,\u200b loving father-in-law of Keiko,\u200b Vinoth and Nushara,\u200b loving grandfather of Ashoka,\u200b Emeni,\u200b Mila,\u200b Amaya and Ellie,\u200b only son of late Mr & Mrs G.P.D. Bandara of Hettipola. Cortege leaves 182/\u200b4 B,\u200b Sapumal Pedesa,\u200b off Stanley Tillekeratne Mawatha,\u200b Nugegoda at 2 p.m. for Cremation at Old Crematorium,\u200b Borella at 3 p.m. on Saturday 11th November 2023.072971"
}