{
  "ut": 1709942400,
  "date_str": "2024-03-09",
  "newspaper_id": "daily-news",
  "url": "https://www.dailynews.lk/2024/03/09/obituaries/439254/obituaries-179/",
  "raw_title": "SENANAYAKE \u2013 MALATHI CHANDIMA",
  "raw_body": "SENANAYAKE \u2013 MALATHI CHANDIMA \u2013 Beloved wife of Kirthi Senanayake, loving mother of Ruvini, Varuni & Rajika, mother-in-law of Dayal, Sheran & Hasantha, grandmother of Jithen & Nayanthara, Avanti, Kyasha & Dhiren. Remains lie at A.F. Raymond Funeral Parlour on Saturday 9th March 2024 from 9.30 a.m. onwards, cortege leaves Parlour at 2.30 p.m. on same day for Cremation at General Cemetery Borella at 3 p.m. (Old Crematorium).\n017617"
}