{
  "ut": 1699920000,
  "date_str": "2023-11-14",
  "newspaper_id": "daily-news",
  "url": "https://www.dailynews.lk/2023/11/14/obituaries/230576/obituaries-104/",
  "raw_title": "COLLINS LEO MILROY",
  "raw_body": "COLLINS LEO MILROY peacefully passed away on 9 Nov. 2023. Cherished husband of Lourdes,\u200b beloved father of Sharon,\u200b father-in-law of Eugene,\u200b son of late James and Emily,\u200b brother of late Ranjini,\u200b Sherwin,\u200b Desmond,\u200b Premilla & Nirupa,\u200b son-in-law of late Xavier & Agnes. Burial in Auckland on 14 November.074115"
}